aiobitrix24/__init__.py
aiobitrix24/_bitrix24.py
aiobitrix24/_builders.py
aiobitrix24/_crm.py
aiobitrix24/exceptions.py
aiobitrix24/methods/__init__.py
aiobitrix24/methods/common.py
aiobitrix24/methods/crm.py
aiobitrix24-0.4.4.dist-info/licenses/LICENSE
aiobitrix24-0.4.4.dist-info/METADATA
aiobitrix24-0.4.4.dist-info/WHEEL
aiobitrix24-0.4.4.dist-info/RECORD
