Metadata-Version: 2.4
Name: aiobitrix24
Version: 0.4.4
Summary: Simple async bitrix-24 rest client
License: MIT
License-File: LICENSE
Keywords: bitrix24,asyncio,httpx
Author: andrpocc
Author-email: andrey.pochatkov@mail.ru
Requires-Python: >=3.10,<4.0
Classifier: License :: OSI Approved :: MIT License
Classifier: Programming Language :: Python :: 3
Classifier: Programming Language :: Python :: 3.10
Classifier: Programming Language :: Python :: 3.11
Classifier: Programming Language :: Python :: 3.12
Classifier: Programming Language :: Python :: 3.13
Classifier: Programming Language :: Python :: 3.14
Classifier: Topic :: Software Development :: Libraries :: Python Modules
Requires-Dist: httpx (>=0.28.1,<0.29.0)
Project-URL: Homepage, https://github.com/andrpocc/aiobitrix24
Project-URL: Repository, https://github.com/andrpocc/aiobitrix24
